{
    "match_id": 101163598,
    "barracks_status_dire": 63,
    "barracks_status_radiant": 63,
    "chat": [
        {
            "time": 0,
            "unit": "Liquid`Korok",
            "key": "gl hf",
            "slot": null,
            "player_slot": null
        },
        {
            "time": 0,
            "unit": "Na`Vi.Sobachka",
            "key": "gl hf",
            "slot": null,
            "player_slot": null
        },
        {
            "time": 0,
            "unit": "Na`Vi.Dendi",
            "key": "\u0438 \u0432\u0430\u043c \u0442\u043e\u0433\u043e-\u0436\u0435",
            "slot": null,
            "player_slot": null
        },
        {
            "time": 0,
            "unit": "Liquid`TC",
            "key": "gl hf",
            "slot": null,
            "player_slot": null
        },
        {
            "time": 0,
            "unit": "Na`Vi.Dendi",
            "key": "gl hf",
            "slot": null,
            "player_slot": null
        },
        {
            "time": 0,
            "unit": "Na`Vi.AA",
            "key": "gl hf",
            "slot": null,
            "player_slot": null
        },
        {
            "time": 0,
            "unit": "Na`Vi.Sobachka",
            "key": "\u0431\u0443\u043b\u044c\u0431\u0430",
            "slot": null,
            "player_slot": null
        },
        {
            "time": 2017,
            "unit": "Liquid`BuLba",
            "key": "gg!",
            "slot": null,
            "player_slot": null
        },
        {
            "time": 2023,
            "unit": "Liquid`TC",
            "key": "gg",
            "slot": null,
            "player_slot": null
        },
        {
            "time": 2023,
            "unit": "Na`Vi.Sobachka",
            "key": "gg",
            "slot": null,
            "player_slot": null
        },
        {
            "time": 2025,
            "unit": "Na`Vi.Puppey",
            "key": "gg",
            "slot": null,
            "player_slot": null
        },
        {
            "time": 2026,
            "unit": "Na`Vi.Dendi",
            "key": "gg",
            "slot": null,
            "player_slot": null
        },
        {
            "time": 2026,
            "unit": "Liquid`ixmike88",
            "key": "gg",
            "slot": null,
            "player_slot": null
        },
        {
            "time": 2026,
            "unit": "Liquid`Korok",
            "key": "gg",
            "slot": null,
            "player_slot": null
        },
        {
            "time": 2027,
            "unit": "Liquid`FLUFF",
            "key": "gg",
            "slot": null,
            "player_slot": null
        },
        {
            "time": 2030,
            "unit": "Na`Vi.AA",
            "key": "g",
            "slot": null,
            "player_slot": null
        }
    ],
    "cluster": 131,
    "cosmetics": {},
    "dire_score": 0,
    "draft_timings": null,
    "duration": 1214,
    "engine": 0,
    "first_blood_time": 104,
    "game_mode": 2,
    "human_players": 10,
    "leagueid": 22,
    "lobby_type": 1,
    "match_seq_num": 93577285,
    "negative_votes": 12,
    "objectives": [
        {
            "time": 964,
            "type": "CHAT_MESSAGE_FIRSTBLOOD",
            "slot": 1,
            "key": 8
        },
        {
            "time": 1336,
            "type": "CHAT_MESSAGE_TOWER_KILL",
            "team": 2,
            "slot": -1
        },
        {
            "time": 1468,
            "type": "CHAT_MESSAGE_TOWER_KILL",
            "team": 2,
            "slot": 3
        },
        {
            "time": 1583,
            "type": "CHAT_MESSAGE_TOWER_KILL",
            "team": 2,
            "slot": 1
        },
        {
            "time": 1862,
            "type": "CHAT_MESSAGE_TOWER_KILL",
            "team": 2,
            "slot": 1
        }
    ],
    "picks_bans": null,
    "positive_votes": 101,
    "radiant_gold_adv": [],
    "radiant_score": 0,
    "radiant_win": false,
    "radiant_xp_adv": [],
    "start_time": 1358365166,
    "teamfights": [],
    "tower_status_dire": 1972,
    "tower_status_radiant": 2047,
    "version": 20,
    "replay_salt": 2089297139,
    "series_id": 0,
    "series_type": 0,
    "radiant_team": {
        "team_id": 36,
        "name": "Natus Vincere",
        "tag": "Na`Vi",
        "logo_url": "https://steamcdn-a.akamaihd.net/apps/dota2/images/team_logos/36.png"
    },
    "dire_team": {
        "team_id": 2163,
        "name": "Team Liquid",
        "tag": "Liquid",
        "logo_url": "https://steamcdn-a.akamaihd.net/apps/dota2/images/team_logos/2163.png"
    },
    "league": {
        "leagueid": 22,
        "ticket": "econ/leagues/subscriptions_d2l_s2",
        "banner": "econ/leagues/subscriptions_d2l_s2_ingame",
        "tier": "professional",
        "name": "RaidCall Dota 2 League Season 2"
    },
    "skill": null,
    "players": [
        {
            "match_id": 101163598,
            "player_slot": 0,
            "ability_upgrades_arr": null,
            "ability_uses": {},
            "ability_targets": null,
            "damage_targets": null,
            "account_id": 87278757,
            "actions": {},
            "additional_units": null,
            "assists": 9,
            "backpack_0": 0,
            "backpack_1": 0,
            "backpack_2": 0,
            "buyback_log": [],
            "camps_stacked": 0,
            "creeps_stacked": 0,
            "damage": {},
            "damage_inflictor": {},
            "damage_inflictor_received": {},
            "damage_taken": {},
            "deaths": 1,
            "denies": 0,
            "dn_t": [],
            "gold": null,
            "gold_per_min": 270,
            "gold_reasons": {},
            "gold_spent": null,
            "gold_t": [],
            "hero_damage": null,
            "hero_healing": null,
            "hero_hits": {},
            "hero_id": 16,
            "item_0": 36,
            "item_1": 180,
            "item_2": 1,
            "item_3": 0,
            "item_4": 0,
            "item_5": 0,
            "item_uses": {},
            "kill_streaks": {},
            "killed": {},
            "killed_by": {},
            "kills": 4,
            "kills_log": [],
            "lane_pos": {},
            "last_hits": 29,
            "leaver_status": 1,
            "level": 10,
            "lh_t": [],
            "life_state": {},
            "max_hero_hit": {
                "value": 0
            },
            "multi_kills": {},
            "obs": {},
            "obs_left_log": [],
            "obs_log": [],
            "obs_placed": 0,
            "party_id": 0,
            "permanent_buffs": null,
            "pings": 4,
            "purchase": {
                "dust": null
            },
            "purchase_log": [],
            "rune_pickups": 0,
            "runes": {},
            "runes_log": [],
            "sen": {},
            "sen_left_log": [],
            "sen_log": [],
            "sen_placed": 0,
            "stuns": 0.0,
            "times": [],
            "tower_damage": null,
            "xp_per_min": 304,
            "xp_reasons": {},
            "xp_t": [],
            "personaname": "Puppey",
            "name": "Puppey",
            "radiant_win": false,
            "start_time": 1358365166,
            "duration": 1214,
            "cluster": 131,
            "lobby_type": 1,
            "game_mode": 2,
            "patch": 7,
            "region": 3,
            "is_radiant": true,
            "win": 0,
            "lose": 1,
            "total_gold": 5463,
            "total_xp": 6150,
            "kills_per_min": 0.19769357495881382,
            "kda": 6.0,
            "abandons": 0,
            "neutral_kills": 0,
            "tower_kills": 0,
            "courier_kills": 0,
            "lane_kills": 0,
            "hero_kills": 0,
            "observer_kills": 0,
            "sentry_kills": 0,
            "roshan_kills": 0,
            "necronomicon_kills": 0,
            "ancient_kills": 0,
            "buyback_count": 0,
            "observer_uses": 0,
            "sentry_uses": 0,
            "lane_efficiency": null,
            "lane_efficiency_pct": null,
            "lane": null,
            "lane_role": null,
            "is_roaming": false,
            "purchase_time": {},
            "first_purchase_time": {},
            "item_win": {},
            "item_usage": {},
            "purchase_tpscroll": null,
            "actions_per_min": 0,
            "life_state_dead": 0,
            "rank_tier": null,
            "cosmetics": [],
            "benchmarks": {
                "gold_per_min": {
                    "raw": 270,
                    "pct": 0.08526764566556135
                },
                "xp_per_min": {
                    "raw": 304,
                    "pct": 0.08195168166745619
                },
                "kills_per_min": {
                    "raw": 0.19769357495881384,
                    "pct": 0.7333017527238276
                },
                "last_hits_per_min": {
                    "raw": 1.4332784184514005,
                    "pct": 0.06584557081951682
                },
                "hero_damage_per_min": {
                    "raw": 0,
                    "pct": 0.0004737091425864519
                },
                "hero_healing_per_min": {
                    "raw": 0,
                    "pct": 0.8882046423495974
                },
                "tower_damage": {},
                "stuns_per_min": {
                    "raw": 0,
                    "pct": 0.0028422548555187117
                },
                "lhten": {}
            }
        },
        {
            "match_id": 101163598,
            "player_slot": 1,
            "ability_upgrades_arr": null,
            "ability_uses": null,
            "ability_targets": null,
            "damage_targets": null,
            "account_id": 89625472,
            "actions": null,
            "additional_units": null,
            "assists": 6,
            "backpack_0": 0,
            "backpack_1": 0,
            "backpack_2": 0,
            "buyback_log": null,
            "camps_stacked": null,
            "creeps_stacked": null,
            "damage": null,
            "damage_inflictor": null,
            "damage_inflictor_received": null,
            "damage_taken": null,
            "deaths": 1,
            "denies": 9,
            "dn_t": null,
            "gold": null,
            "gold_per_min": 629,
            "gold_reasons": null,
            "gold_spent": null,
            "gold_t": null,
            "hero_damage": null,
            "hero_healing": null,
            "hero_hits": null,
            "hero_id": 72,
            "item_0": 50,
            "item_1": 116,
            "item_2": 152,
            "item_3": 212,
            "item_4": 164,
            "item_5": 46,
            "item_uses": null,
            "kill_streaks": null,
            "killed": null,
            "killed_by": null,
            "kills": 4,
            "kills_log": null,
            "lane_pos": null,
            "last_hits": 160,
            "leaver_status": 1,
            "level": 14,
            "lh_t": null,
            "life_state": null,
            "max_hero_hit": null,
            "multi_kills": null,
            "obs": null,
            "obs_left_log": null,
            "obs_log": null,
            "obs_placed": null,
            "party_id": 0,
            "permanent_buffs": null,
            "pings": null,
            "purchase": null,
            "purchase_log": null,
            "rune_pickups": null,
            "runes": null,
            "runes_log": null,
            "sen": null,
            "sen_left_log": null,
            "sen_log": null,
            "sen_placed": null,
            "stuns": null,
            "times": null,
            "tower_damage": null,
            "xp_per_min": 586,
            "xp_reasons": null,
            "xp_t": null,
            "personaname": "Aleksandr Yurich",
            "name": null,
            "radiant_win": false,
            "start_time": 1358365166,
            "duration": 1214,
            "cluster": 131,
            "lobby_type": 1,
            "game_mode": 2,
            "patch": 7,
            "region": 3,
            "is_radiant": true,
            "win": 0,
            "lose": 1,
            "total_gold": 12726,
            "total_xp": 11856,
            "kills_per_min": 0.19769357495881382,
            "kda": 5.0,
            "abandons": 0,
            "neutral_kills": null,
            "tower_kills": null,
            "courier_kills": null,
            "lane_kills": null,
            "hero_kills": null,
            "observer_kills": null,
            "sentry_kills": null,
            "roshan_kills": null,
            "necronomicon_kills": null,
            "ancient_kills": null,
            "buyback_count": null,
            "observer_uses": null,
            "sentry_uses": null,
            "lane_efficiency": null,
            "lane_efficiency_pct": null,
            "lane": null,
            "lane_role": null,
            "is_roaming": null,
            "purchase_time": null,
            "first_purchase_time": null,
            "item_win": null,
            "item_usage": null,
            "purchase_tpscroll": null,
            "actions_per_min": null,
            "life_state_dead": null,
            "rank_tier": 80,
            "cosmetics": [],
            "benchmarks": {
                "gold_per_min": {
                    "raw": 629,
                    "pct": 0.9251497005988024
                },
                "xp_per_min": {
                    "raw": 586,
                    "pct": 0.6497005988023952
                },
                "kills_per_min": {
                    "raw": 0.19769357495881384,
                    "pct": 0.5958083832335329
                },
                "last_hits_per_min": {
                    "raw": 7.907742998352553,
                    "pct": 0.9221556886227545
                },
                "hero_damage_per_min": {
                    "raw": 0,
                    "pct": 0.0029940119760479044
                },
                "hero_healing_per_min": {
                    "raw": 0,
                    "pct": 0.9431137724550899
                },
                "tower_damage": {},
                "stuns_per_min": {
                    "raw": 0,
                    "pct": 0.014970059880239521
                },
                "lhten": {}
            }
        },
        {
            "match_id": 101163598,
            "player_slot": 2,
            "ability_upgrades_arr": null,
            "ability_uses": null,
            "ability_targets": null,
            "damage_targets": null,
            "account_id": 70388657,
            "actions": null,
            "additional_units": null,
            "assists": 10,
            "backpack_0": 0,
            "backpack_1": 0,
            "backpack_2": 0,
            "buyback_log": null,
            "camps_stacked": null,
            "creeps_stacked": null,
            "damage": null,
            "damage_inflictor": null,
            "damage_inflictor_received": null,
            "damage_taken": null,
            "deaths": 0,
            "denies": 16,
            "dn_t": null,
            "gold": null,
            "gold_per_min": 379,
            "gold_reasons": null,
            "gold_spent": null,
            "gold_t": null,
            "hero_damage": null,
            "hero_healing": null,
            "hero_hits": null,
            "hero_id": 65,
            "item_0": 46,
            "item_1": 41,
            "item_2": 37,
            "item_3": 36,
            "item_4": 1,
            "item_5": 214,
            "item_uses": null,
            "kill_streaks": null,
            "killed": null,
            "killed_by": null,
            "kills": 6,
            "kills_log": null,
            "lane_pos": null,
            "last_hits": 67,
            "leaver_status": 1,
            "level": 13,
            "lh_t": null,
            "life_state": null,
            "max_hero_hit": null,
            "multi_kills": null,
            "obs": null,
            "obs_left_log": null,
            "obs_log": null,
            "obs_placed": null,
            "party_id": 0,
            "permanent_buffs": null,
            "pings": null,
            "purchase": null,
            "purchase_log": null,
            "rune_pickups": null,
            "runes": null,
            "runes_log": null,
            "sen": null,
            "sen_left_log": null,
            "sen_log": null,
            "sen_placed": null,
            "stuns": null,
            "times": null,
            "tower_damage": null,
            "xp_per_min": 502,
            "xp_reasons": null,
            "xp_t": null,
            "personaname": "Garena",
            "name": "Dendi",
            "radiant_win": false,
            "start_time": 1358365166,
            "duration": 1214,
            "cluster": 131,
            "lobby_type": 1,
            "game_mode": 2,
            "patch": 7,
            "region": 3,
            "is_radiant": true,
            "win": 0,
            "lose": 1,
            "total_gold": 7668,
            "total_xp": 10157,
            "kills_per_min": 0.29654036243822074,
            "kda": 16.0,
            "abandons": 0,
            "neutral_kills": null,
            "tower_kills": null,
            "courier_kills": null,
            "lane_kills": null,
            "hero_kills": null,
            "observer_kills": null,
            "sentry_kills": null,
            "roshan_kills": null,
            "necronomicon_kills": null,
            "ancient_kills": null,
            "buyback_count": null,
            "observer_uses": null,
            "sentry_uses": null,
            "lane_efficiency": null,
            "lane_efficiency_pct": null,
            "lane": null,
            "lane_role": null,
            "is_roaming": null,
            "purchase_time": null,
            "first_purchase_time": null,
            "item_win": null,
            "item_usage": null,
            "purchase_tpscroll": null,
            "actions_per_min": null,
            "life_state_dead": null,
            "rank_tier": null,
            "cosmetics": [],
            "benchmarks": {
                "gold_per_min": {
                    "raw": 379,
                    "pct": 0.6854460093896714
                },
                "xp_per_min": {
                    "raw": 502,
                    "pct": 0.6666666666666666
                },
                "kills_per_min": {
                    "raw": 0.29654036243822074,
                    "pct": 0.8591549295774648
                },
                "last_hits_per_min": {
                    "raw": 3.3113673805601316,
                    "pct": 0.7793427230046949
                },
                "hero_damage_per_min": {
                    "raw": 0,
                    "pct": 0.009389671361502348
                },
                "hero_healing_per_min": {
                    "raw": 0,
                    "pct": 0.8826291079812206
                },
                "tower_damage": {},
                "stuns_per_min": {
                    "raw": 0,
                    "pct": 0.023474178403755867
                },
                "lhten": {}
            }
        },
        {
            "match_id": 101163598,
            "player_slot": 3,
            "ability_upgrades_arr": null,
            "ability_uses": null,
            "ability_targets": null,
            "damage_targets": null,
            "account_id": 89326318,
            "actions": null,
            "additional_units": null,
            "assists": 6,
            "backpack_0": 0,
            "backpack_1": 0,
            "backpack_2": 0,
            "buyback_log": null,
            "camps_stacked": null,
            "creeps_stacked": null,
            "damage": null,
            "damage_inflictor": null,
            "damage_inflictor_received": null,
            "damage_taken": null,
            "deaths": 0,
            "denies": 0,
            "dn_t": null,
            "gold": null,
            "gold_per_min": 398,
            "gold_reasons": null,
            "gold_spent": null,
            "gold_t": null,
            "hero_damage": null,
            "hero_healing": null,
            "hero_hits": null,
            "hero_id": 55,
            "item_0": 79,
            "item_1": 34,
            "item_2": 178,
            "item_3": 60,
            "item_4": 180,
            "item_5": 46,
            "item_uses": null,
            "kill_streaks": null,
            "killed": null,
            "killed_by": null,
            "kills": 3,
            "kills_log": null,
            "lane_pos": null,
            "last_hits": 106,
            "leaver_status": 1,
            "level": 13,
            "lh_t": null,
            "life_state": null,
            "max_hero_hit": null,
            "multi_kills": null,
            "obs": null,
            "obs_left_log": null,
            "obs_log": null,
            "obs_placed": null,
            "party_id": 0,
            "permanent_buffs": null,
            "pings": null,
            "purchase": null,
            "purchase_log": null,
            "rune_pickups": null,
            "runes": null,
            "runes_log": null,
            "sen": null,
            "sen_left_log": null,
            "sen_log": null,
            "sen_placed": null,
            "stuns": null,
            "times": null,
            "tower_damage": null,
            "xp_per_min": 485,
            "xp_reasons": null,
            "xp_t": null,
            "personaname": "wtfrofl",
            "name": null,
            "radiant_win": false,
            "start_time": 1358365166,
            "duration": 1214,
            "cluster": 131,
            "lobby_type": 1,
            "game_mode": 2,
            "patch": 7,
            "region": 3,
            "is_radiant": true,
            "win": 0,
            "lose": 1,
            "total_gold": 8052,
            "total_xp": 9813,
            "kills_per_min": 0.14827018121911037,
            "kda": 9.0,
            "abandons": 0,
            "neutral_kills": null,
            "tower_kills": null,
            "courier_kills": null,
            "lane_kills": null,
            "hero_kills": null,
            "observer_kills": null,
            "sentry_kills": null,
            "roshan_kills": null,
            "necronomicon_kills": null,
            "ancient_kills": null,
            "buyback_count": null,
            "observer_uses": null,
            "sentry_uses": null,
            "lane_efficiency": null,
            "lane_efficiency_pct": null,
            "lane": null,
            "lane_role": null,
            "is_roaming": null,
            "purchase_time": null,
            "first_purchase_time": null,
            "item_win": null,
            "item_usage": null,
            "purchase_tpscroll": null,
            "actions_per_min": null,
            "life_state_dead": null,
            "rank_tier": 74,
            "cosmetics": [],
            "benchmarks": {
                "gold_per_min": {
                    "raw": 398,
                    "pct": 0.48936170212765956
                },
                "xp_per_min": {
                    "raw": 485,
                    "pct": 0.49427168576104746
                },
                "kills_per_min": {
                    "raw": 0.14827018121911037,
                    "pct": 0.646481178396072
                },
                "last_hits_per_min": {
                    "raw": 5.238879736408567,
                    "pct": 0.855973813420622
                },
                "hero_damage_per_min": {
                    "raw": 0,
                    "pct": 0.0016366612111292963
                },
                "hero_healing_per_min": {
                    "raw": 0,
                    "pct": 0.3044189852700491
                },
                "tower_damage": {},
                "stuns_per_min": {
                    "raw": 0,
                    "pct": 0.03273322422258593
                },
                "lhten": {}
            }
        },
        {
            "match_id": 101163598,
            "player_slot": 4,
            "ability_upgrades_arr": null,
            "ability_uses": null,
            "ability_targets": null,
            "damage_targets": null,
            "account_id": 107644273,
            "actions": null,
            "additional_units": null,
            "assists": 4,
            "backpack_0": 0,
            "backpack_1": 0,
            "backpack_2": 0,
            "buyback_log": null,
            "camps_stacked": null,
            "creeps_stacked": null,
            "damage": null,
            "damage_inflictor": null,
            "damage_inflictor_received": null,
            "damage_taken": null,
            "deaths": 2,
            "denies": 2,
            "dn_t": null,
            "gold": null,
            "gold_per_min": 231,
            "gold_reasons": null,
            "gold_spent": null,
            "gold_t": null,
            "hero_damage": null,
            "hero_healing": null,
            "hero_hits": null,
            "hero_id": 86,
            "item_0": 16,
            "item_1": 36,
            "item_2": 180,
            "item_3": 0,
            "item_4": 0,
            "item_5": 0,
            "item_uses": null,
            "kill_streaks": null,
            "killed": null,
            "killed_by": null,
            "kills": 2,
            "kills_log": null,
            "lane_pos": null,
            "last_hits": 28,
            "leaver_status": 1,
            "level": 9,
            "lh_t": null,
            "life_state": null,
            "max_hero_hit": null,
            "multi_kills": null,
            "obs": null,
            "obs_left_log": null,
            "obs_log": null,
            "obs_placed": null,
            "party_id": 0,
            "permanent_buffs": null,
            "pings": null,
            "purchase": null,
            "purchase_log": null,
            "rune_pickups": null,
            "runes": null,
            "runes_log": null,
            "sen": null,
            "sen_left_log": null,
            "sen_log": null,
            "sen_placed": null,
            "stuns": null,
            "times": null,
            "tower_damage": null,
            "xp_per_min": 224,
            "xp_reasons": null,
            "xp_t": null,
            "personaname": "Jolly Joker",
            "name": null,
            "radiant_win": false,
            "start_time": 1358365166,
            "duration": 1214,
            "cluster": 131,
            "lobby_type": 1,
            "game_mode": 2,
            "patch": 7,
            "region": 3,
            "is_radiant": true,
            "win": 0,
            "lose": 1,
            "total_gold": 4673,
            "total_xp": 4532,
            "kills_per_min": 0.09884678747940691,
            "kda": 2.0,
            "abandons": 0,
            "neutral_kills": null,
            "tower_kills": null,
            "courier_kills": null,
            "lane_kills": null,
            "hero_kills": null,
            "observer_kills": null,
            "sentry_kills": null,
            "roshan_kills": null,
            "necronomicon_kills": null,
            "ancient_kills": null,
            "buyback_count": null,
            "observer_uses": null,
            "sentry_uses": null,
            "lane_efficiency": null,
            "lane_efficiency_pct": null,
            "lane": null,
            "lane_role": null,
            "is_roaming": null,
            "purchase_time": null,
            "first_purchase_time": null,
            "item_win": null,
            "item_usage": null,
            "purchase_tpscroll": null,
            "actions_per_min": null,
            "life_state_dead": null,
            "rank_tier": 74,
            "cosmetics": [],
            "benchmarks": {
                "gold_per_min": {
                    "raw": 231,
                    "pct": 0.10697674418604651
                },
                "xp_per_min": {
                    "raw": 224,
                    "pct": 0.04709302325581395
                },
                "kills_per_min": {
                    "raw": 0.09884678747940692,
                    "pct": 0.40581395348837207
                },
                "last_hits_per_min": {
                    "raw": 1.383855024711697,
                    "pct": 0.32063953488372093
                },
                "hero_damage_per_min": {
                    "raw": 0,
                    "pct": 0.0017441860465116279
                },
                "hero_healing_per_min": {
                    "raw": 0,
                    "pct": 0.5927325581395348
                },
                "tower_damage": {},
                "stuns_per_min": {
                    "raw": 0,
                    "pct": 0.0029069767441860465
                },
                "lhten": {}
            }
        },
        {
            "match_id": 101163598,
            "player_slot": 128,
            "ability_upgrades_arr": null,
            "ability_uses": null,
            "ability_targets": null,
            "damage_targets": null,
            "account_id": 67601693,
            "actions": null,
            "additional_units": null,
            "assists": 0,
            "backpack_0": 0,
            "backpack_1": 0,
            "backpack_2": 0,
            "buyback_log": null,
            "camps_stacked": null,
            "creeps_stacked": null,
            "damage": null,
            "damage_inflictor": null,
            "damage_inflictor_received": null,
            "damage_taken": null,
            "deaths": 3,
            "denies": 24,
            "dn_t": null,
            "gold": null,
            "gold_per_min": 475,
            "gold_reasons": null,
            "gold_spent": null,
            "gold_t": null,
            "hero_damage": null,
            "hero_healing": null,
            "hero_hits": null,
            "hero_id": 54,
            "item_0": 151,
            "item_1": 11,
            "item_2": 0,
            "item_3": 65,
            "item_4": 50,
            "item_5": 0,
            "item_uses": null,
            "kill_streaks": null,
            "killed": null,
            "killed_by": null,
            "kills": 3,
            "kills_log": null,
            "lane_pos": null,
            "last_hits": 132,
            "leaver_status": 1,
            "level": 13,
            "lh_t": null,
            "life_state": null,
            "max_hero_hit": null,
            "multi_kills": null,
            "obs": null,
            "obs_left_log": null,
            "obs_log": null,
            "obs_placed": null,
            "party_id": 0,
            "permanent_buffs": null,
            "pings": null,
            "purchase": null,
            "purchase_log": null,
            "rune_pickups": null,
            "runes": null,
            "runes_log": null,
            "sen": null,
            "sen_left_log": null,
            "sen_log": null,
            "sen_placed": null,
            "stuns": null,
            "times": null,
            "tower_damage": null,
            "xp_per_min": 504,
            "xp_reasons": null,
            "xp_t": null,
            "personaname": "`TC`",
            "name": null,
            "radiant_win": false,
            "start_time": 1358365166,
            "duration": 1214,
            "cluster": 131,
            "lobby_type": 1,
            "game_mode": 2,
            "patch": 7,
            "region": 3,
            "is_radiant": false,
            "win": 1,
            "lose": 0,
            "total_gold": 9610,
            "total_xp": 10197,
            "kills_per_min": 0.14827018121911037,
            "kda": 0.0,
            "abandons": 0,
            "neutral_kills": null,
            "tower_kills": null,
            "courier_kills": null,
            "lane_kills": null,
            "hero_kills": null,
            "observer_kills": null,
            "sentry_kills": null,
            "roshan_kills": null,
            "necronomicon_kills": null,
            "ancient_kills": null,
            "buyback_count": null,
            "observer_uses": null,
            "sentry_uses": null,
            "lane_efficiency": null,
            "lane_efficiency_pct": null,
            "lane": null,
            "lane_role": null,
            "is_roaming": null,
            "purchase_time": null,
            "first_purchase_time": null,
            "item_win": null,
            "item_usage": null,
            "purchase_tpscroll": null,
            "actions_per_min": null,
            "life_state_dead": null,
            "rank_tier": null,
            "cosmetics": [],
            "benchmarks": {
                "gold_per_min": {
                    "raw": 475,
                    "pct": 0.5397727272727273
                },
                "xp_per_min": {
                    "raw": 504,
                    "pct": 0.375
                },
                "kills_per_min": {
                    "raw": 0.14827018121911037,
                    "pct": 0.4318181818181818
                },
                "last_hits_per_min": {
                    "raw": 6.523887973640857,
                    "pct": 0.8560606060606061
                },
                "hero_damage_per_min": {
                    "raw": 0,
                    "pct": 0
                },
                "hero_healing_per_min": {
                    "raw": 0,
                    "pct": 0.00946969696969697
                },
                "tower_damage": {},
                "stuns_per_min": {
                    "raw": 0,
                    "pct": 0.5890151515151515
                },
                "lhten": {}
            }
        },
        {
            "match_id": 101163598,
            "player_slot": 129,
            "ability_upgrades_arr": null,
            "ability_uses": null,
            "ability_targets": null,
            "damage_targets": null,
            "account_id": 1185644,
            "actions": null,
            "additional_units": null,
            "assists": 2,
            "backpack_0": 0,
            "backpack_1": 0,
            "backpack_2": 0,
            "buyback_log": null,
            "camps_stacked": null,
            "creeps_stacked": null,
            "damage": null,
            "damage_inflictor": null,
            "damage_inflictor_received": null,
            "damage_taken": null,
            "deaths": 5,
            "denies": 3,
            "dn_t": null,
            "gold": null,
            "gold_per_min": 151,
            "gold_reasons": null,
            "gold_spent": null,
            "gold_t": null,
            "hero_damage": null,
            "hero_healing": null,
            "hero_hits": null,
            "hero_id": 13,
            "item_0": 36,
            "item_1": 46,
            "item_2": 16,
            "item_3": 63,
            "item_4": 16,
            "item_5": 16,
            "item_uses": null,
            "kill_streaks": null,
            "killed": null,
            "killed_by": null,
            "kills": 0,
            "kills_log": null,
            "lane_pos": null,
            "last_hits": 34,
            "leaver_status": 1,
            "level": 8,
            "lh_t": null,
            "life_state": null,
            "max_hero_hit": null,
            "multi_kills": null,
            "obs": null,
            "obs_left_log": null,
            "obs_log": null,
            "obs_placed": null,
            "party_id": 0,
            "permanent_buffs": null,
            "pings": null,
            "purchase": null,
            "purchase_log": null,
            "rune_pickups": null,
            "runes": null,
            "runes_log": null,
            "sen": null,
            "sen_left_log": null,
            "sen_log": null,
            "sen_placed": null,
            "stuns": null,
            "times": null,
            "tower_damage": null,
            "xp_per_min": 210,
            "xp_reasons": null,
            "xp_t": null,
            "personaname": "K!",
            "name": null,
            "radiant_win": false,
            "start_time": 1358365166,
            "duration": 1214,
            "cluster": 131,
            "lobby_type": 1,
            "game_mode": 2,
            "patch": 7,
            "region": 3,
            "is_radiant": false,
            "win": 1,
            "lose": 0,
            "total_gold": 3055,
            "total_xp": 4249,
            "kills_per_min": null,
            "kda": 0.0,
            "abandons": 0,
            "neutral_kills": null,
            "tower_kills": null,
            "courier_kills": null,
            "lane_kills": null,
            "hero_kills": null,
            "observer_kills": null,
            "sentry_kills": null,
            "roshan_kills": null,
            "necronomicon_kills": null,
            "ancient_kills": null,
            "buyback_count": null,
            "observer_uses": null,
            "sentry_uses": null,
            "lane_efficiency": null,
            "lane_efficiency_pct": null,
            "lane": null,
            "lane_role": null,
            "is_roaming": null,
            "purchase_time": null,
            "first_purchase_time": null,
            "item_win": null,
            "item_usage": null,
            "purchase_tpscroll": null,
            "actions_per_min": null,
            "life_state_dead": null,
            "rank_tier": 75,
            "cosmetics": [],
            "benchmarks": {
                "gold_per_min": {
                    "raw": 151,
                    "pct": 0.003738317757009346
                },
                "xp_per_min": {
                    "raw": 210,
                    "pct": 0.014953271028037384
                },
                "kills_per_min": {
                    "raw": 0,
                    "pct": 0.024299065420560748
                },
                "last_hits_per_min": {
                    "raw": 1.6803953871499175,
                    "pct": 0.044859813084112146
                },
                "hero_damage_per_min": {
                    "raw": 0,
                    "pct": 0
                },
                "hero_healing_per_min": {
                    "raw": 0,
                    "pct": 0.7981308411214953
                },
                "tower_damage": {},
                "stuns_per_min": {
                    "raw": 0,
                    "pct": 0.009345794392523364
                },
                "lhten": {}
            }
        },
        {
            "match_id": 101163598,
            "player_slot": 130,
            "ability_upgrades_arr": null,
            "ability_uses": null,
            "ability_targets": null,
            "damage_targets": null,
            "account_id": 41470731,
            "actions": null,
            "additional_units": null,
            "assists": 3,
            "backpack_0": 0,
            "backpack_1": 0,
            "backpack_2": 0,
            "buyback_log": null,
            "camps_stacked": null,
            "creeps_stacked": null,
            "damage": null,
            "damage_inflictor": null,
            "damage_inflictor_received": null,
            "damage_taken": null,
            "deaths": 5,
            "denies": 0,
            "dn_t": null,
            "gold": null,
            "gold_per_min": 119,
            "gold_reasons": null,
            "gold_spent": null,
            "gold_t": null,
            "hero_damage": null,
            "hero_healing": null,
            "hero_hits": null,
            "hero_id": 20,
            "item_0": 29,
            "item_1": 34,
            "item_2": 73,
            "item_3": 0,
            "item_4": 16,
            "item_5": 46,
            "item_uses": null,
            "kill_streaks": null,
            "killed": null,
            "killed_by": null,
            "kills": 1,
            "kills_log": null,
            "lane_pos": null,
            "last_hits": 10,
            "leaver_status": 1,
            "level": 7,
            "lh_t": null,
            "life_state": null,
            "max_hero_hit": null,
            "multi_kills": null,
            "obs": null,
            "obs_left_log": null,
            "obs_log": null,
            "obs_placed": null,
            "party_id": 0,
            "permanent_buffs": null,
            "pings": null,
            "purchase": null,
            "purchase_log": null,
            "rune_pickups": null,
            "runes": null,
            "runes_log": null,
            "sen": null,
            "sen_left_log": null,
            "sen_log": null,
            "sen_placed": null,
            "stuns": null,
            "times": null,
            "tower_damage": null,
            "xp_per_min": 130,
            "xp_reasons": null,
            "xp_t": null,
            "personaname": "Brian",
            "name": "FLUFFNSTUFF",
            "radiant_win": false,
            "start_time": 1358365166,
            "duration": 1214,
            "cluster": 131,
            "lobby_type": 1,
            "game_mode": 2,
            "patch": 7,
            "region": 3,
            "is_radiant": false,
            "win": 1,
            "lose": 0,
            "total_gold": 2407,
            "total_xp": 2630,
            "kills_per_min": 0.049423393739703454,
            "kda": 0.0,
            "abandons": 0,
            "neutral_kills": null,
            "tower_kills": null,
            "courier_kills": null,
            "lane_kills": null,
            "hero_kills": null,
            "observer_kills": null,
            "sentry_kills": null,
            "roshan_kills": null,
            "necronomicon_kills": null,
            "ancient_kills": null,
            "buyback_count": null,
            "observer_uses": null,
            "sentry_uses": null,
            "lane_efficiency": null,
            "lane_efficiency_pct": null,
            "lane": null,
            "lane_role": null,
            "is_roaming": null,
            "purchase_time": null,
            "first_purchase_time": null,
            "item_win": null,
            "item_usage": null,
            "purchase_tpscroll": null,
            "actions_per_min": null,
            "life_state_dead": null,
            "rank_tier": null,
            "cosmetics": [],
            "benchmarks": {
                "gold_per_min": {
                    "raw": 119,
                    "pct": 0
                },
                "xp_per_min": {
                    "raw": 130,
                    "pct": 0.007291666666666667
                },
                "kills_per_min": {
                    "raw": 0.04942339373970346,
                    "pct": 0.27291666666666664
                },
                "last_hits_per_min": {
                    "raw": 0.4942339373970346,
                    "pct": 0.10833333333333334
                },
                "hero_damage_per_min": {
                    "raw": 0,
                    "pct": 0
                },
                "hero_healing_per_min": {
                    "raw": 0,
                    "pct": 0.709375
                },
                "tower_damage": {},
                "stuns_per_min": {
                    "raw": 0,
                    "pct": 0.0010416666666666667
                },
                "lhten": {}
            }
        },
        {
            "match_id": 101163598,
            "player_slot": 131,
            "ability_upgrades_arr": null,
            "ability_uses": null,
            "ability_targets": null,
            "damage_targets": null,
            "account_id": 30237211,
            "actions": null,
            "additional_units": null,
            "assists": 3,
            "backpack_0": 0,
            "backpack_1": 0,
            "backpack_2": 0,
            "buyback_log": null,
            "camps_stacked": null,
            "creeps_stacked": null,
            "damage": null,
            "damage_inflictor": null,
            "damage_inflictor_received": null,
            "damage_taken": null,
            "deaths": 4,
            "denies": 3,
            "dn_t": null,
            "gold": null,
            "gold_per_min": 129,
            "gold_reasons": null,
            "gold_spent": null,
            "gold_t": null,
            "hero_damage": null,
            "hero_healing": null,
            "hero_hits": null,
            "hero_id": 97,
            "item_0": 41,
            "item_1": 36,
            "item_2": 0,
            "item_3": 29,
            "item_4": 182,
            "item_5": 0,
            "item_uses": null,
            "kill_streaks": null,
            "killed": null,
            "killed_by": null,
            "kills": 0,
            "kills_log": null,
            "lane_pos": null,
            "last_hits": 20,
            "leaver_status": 1,
            "level": 7,
            "lh_t": null,
            "life_state": null,
            "max_hero_hit": null,
            "multi_kills": null,
            "obs": null,
            "obs_left_log": null,
            "obs_log": null,
            "obs_placed": null,
            "party_id": 0,
            "permanent_buffs": null,
            "pings": null,
            "purchase": null,
            "purchase_log": null,
            "rune_pickups": null,
            "runes": null,
            "runes_log": null,
            "sen": null,
            "sen_left_log": null,
            "sen_log": null,
            "sen_placed": null,
            "stuns": null,
            "times": null,
            "tower_damage": null,
            "xp_per_min": 147,
            "xp_reasons": null,
            "xp_t": null,
            "personaname": "Kagami",
            "name": "BuLba",
            "radiant_win": false,
            "start_time": 1358365166,
            "duration": 1214,
            "cluster": 131,
            "lobby_type": 1,
            "game_mode": 2,
            "patch": 7,
            "region": 3,
            "is_radiant": false,
            "win": 1,
            "lose": 0,
            "total_gold": 2610,
            "total_xp": 2974,
            "kills_per_min": null,
            "kda": 0.0,
            "abandons": 0,
            "neutral_kills": null,
            "tower_kills": null,
            "courier_kills": null,
            "lane_kills": null,
            "hero_kills": null,
            "observer_kills": null,
            "sentry_kills": null,
            "roshan_kills": null,
            "necronomicon_kills": null,
            "ancient_kills": null,
            "buyback_count": null,
            "observer_uses": null,
            "sentry_uses": null,
            "lane_efficiency": null,
            "lane_efficiency_pct": null,
            "lane": null,
            "lane_role": null,
            "is_roaming": null,
            "purchase_time": null,
            "first_purchase_time": null,
            "item_win": null,
            "item_usage": null,
            "purchase_tpscroll": null,
            "actions_per_min": null,
            "life_state_dead": null,
            "rank_tier": 80,
            "cosmetics": [],
            "benchmarks": {
                "gold_per_min": {
                    "raw": 129,
                    "pct": 0.0004805382027871216
                },
                "xp_per_min": {
                    "raw": 147,
                    "pct": 0.003363767419509851
                },
                "kills_per_min": {
                    "raw": 0,
                    "pct": 0.08649687650168188
                },
                "last_hits_per_min": {
                    "raw": 0.9884678747940692,
                    "pct": 0.03940413262854397
                },
                "hero_damage_per_min": {
                    "raw": 0,
                    "pct": 0
                },
                "hero_healing_per_min": {
                    "raw": 0,
                    "pct": 0.7414704469005285
                },
                "tower_damage": {},
                "stuns_per_min": {
                    "raw": 0,
                    "pct": 0.0014416146083613647
                },
                "lhten": {}
            }
        },
        {
            "match_id": 101163598,
            "player_slot": 132,
            "ability_upgrades_arr": null,
            "ability_uses": null,
            "ability_targets": null,
            "damage_targets": null,
            "account_id": 86715129,
            "actions": null,
            "additional_units": null,
            "assists": 1,
            "backpack_0": 0,
            "backpack_1": 0,
            "backpack_2": 0,
            "buyback_log": null,
            "camps_stacked": null,
            "creeps_stacked": null,
            "damage": null,
            "damage_inflictor": null,
            "damage_inflictor_received": null,
            "damage_taken": null,
            "deaths": 2,
            "denies": 0,
            "dn_t": null,
            "gold": null,
            "gold_per_min": 155,
            "gold_reasons": null,
            "gold_spent": null,
            "gold_t": null,
            "hero_damage": null,
            "hero_healing": null,
            "hero_hits": null,
            "hero_id": 90,
            "item_0": 43,
            "item_1": 0,
            "item_2": 214,
            "item_3": 0,
            "item_4": 42,
            "item_5": 36,
            "item_uses": null,
            "kill_streaks": null,
            "killed": null,
            "killed_by": null,
            "kills": 0,
            "kills_log": null,
            "lane_pos": null,
            "last_hits": 36,
            "leaver_status": 1,
            "level": 7,
            "lh_t": null,
            "life_state": null,
            "max_hero_hit": null,
            "multi_kills": null,
            "obs": null,
            "obs_left_log": null,
            "obs_log": null,
            "obs_placed": null,
            "party_id": 0,
            "permanent_buffs": null,
            "pings": null,
            "purchase": null,
            "purchase_log": null,
            "rune_pickups": null,
            "runes": null,
            "runes_log": null,
            "sen": null,
            "sen_left_log": null,
            "sen_log": null,
            "sen_placed": null,
            "stuns": null,
            "times": null,
            "tower_damage": null,
            "xp_per_min": 143,
            "xp_reasons": null,
            "xp_t": null,
            "personaname": "ixmike88",
            "name": "ixmike88",
            "radiant_win": false,
            "start_time": 1358365166,
            "duration": 1214,
            "cluster": 131,
            "lobby_type": 1,
            "game_mode": 2,
            "patch": 7,
            "region": 3,
            "is_radiant": false,
            "win": 1,
            "lose": 0,
            "total_gold": 3136,
            "total_xp": 2893,
            "kills_per_min": null,
            "kda": 0.0,
            "abandons": 0,
            "neutral_kills": null,
            "tower_kills": null,
            "courier_kills": null,
            "lane_kills": null,
            "hero_kills": null,
            "observer_kills": null,
            "sentry_kills": null,
            "roshan_kills": null,
            "necronomicon_kills": null,
            "ancient_kills": null,
            "buyback_count": null,
            "observer_uses": null,
            "sentry_uses": null,
            "lane_efficiency": null,
            "lane_efficiency_pct": null,
            "lane": null,
            "lane_role": null,
            "is_roaming": null,
            "purchase_time": null,
            "first_purchase_time": null,
            "item_win": null,
            "item_usage": null,
            "purchase_tpscroll": null,
            "actions_per_min": null,
            "life_state_dead": null,
            "rank_tier": 80,
            "cosmetics": [],
            "benchmarks": {
                "gold_per_min": {
                    "raw": 155,
                    "pct": 0.0020847810979847115
                },
                "xp_per_min": {
                    "raw": 143,
                    "pct": 0.002779708130646282
                },
                "kills_per_min": {
                    "raw": 0,
                    "pct": 0.11952744961779013
                },
                "last_hits_per_min": {
                    "raw": 1.7792421746293245,
                    "pct": 0.30785267546907574
                },
                "hero_damage_per_min": {
                    "raw": 0,
                    "pct": 0.0006949270326615705
                },
                "hero_healing_per_min": {
                    "raw": 0,
                    "pct": 0.6365531619179986
                },
                "tower_damage": {},
                "stuns_per_min": {
                    "raw": 0,
                    "pct": 0.8220986796386379
                },
                "lhten": {}
            }
        }
    ],
    "patch": 7,
    "region": 3,
    "all_word_counts": {
        "gl": 5,
        "hf": 5,
        "-": 1,
        "gg": 8,
        "g": 1
    },
    "my_word_counts": {},
    "throw": null,
    "loss": null,
    "replay_url": "http://replay131.valve.net/570/101163598_2089297139.dem.bz2"
}